README.rst
setup.py
tests/__init__.py
tests/core_tests.py
validict/__init__.py
validict.egg-info/PKG-INFO
validict.egg-info/SOURCES.txt
validict.egg-info/dependency_links.txt
validict.egg-info/pbr.json
validict.egg-info/top_level.txt