Metadata-Version: 1.1
Name: validict
Version: 1.5
Summary: A simple validation module
Home-page: https://github.com/josefdlange/validict
Author: Josef Lange
Author-email: josef.d.lange@me.com
License: MIT
Keywords: validation dictionary validate valid list json request validator
Platform: UNKNOWN
Classifier: Topic :: Utilities
Classifier: License :: OSI Approved :: MIT License
